MANIFEST.in
setup.cfg
setup.py
Examples/EmailExample.py
Examples/Main.py
Examples/ZPTExample.py
Examples/__init__.py
Examples/templates/EmailExample.pt
Examples/templates/EmailExample_email.pt
Examples/templates/EmailExample_error.pt
Examples/templates/Main.pt
Examples/templates/standard_template.pt
ZPTKit/ExceptionFormatter.py
ZPTKit/Properties.py
ZPTKit/__init__.py
ZPTKit/emailtemplate.py
ZPTKit/htmlrender.py
ZPTKit/paster_templates.py
ZPTKit/resourcecomponent.py
ZPTKit/shadowdict.py
ZPTKit/templatetools.py
ZPTKit/zptcomponent.py
ZPTKit/zptwareweb.py
ZPTKit.egg-info/PKG-INFO
ZPTKit.egg-info/SOURCES.txt
ZPTKit.egg-info/entry_points.txt
ZPTKit.egg-info/requires.txt
ZPTKit.egg-info/top_level.txt
ZPTKit/backports/UserDict.py
ZPTKit/backports/__init__.py
ZPTKit/backports/textwrap.py
ZPTKit/paster_templates/zpt/+package+/templates/blank.pt
ZPTKit/paster_templates/zpt/+package+/templates/index.pt
ZPTKit/paster_templates/zpt/+package+/templates/standard_template.pt
disttools/build
disttools/convert_index.py
disttools/imagescape_default.css
disttools/upload-docs
docs/default.css
docs/index.txt
tests/conftest.py
tests/test_htmlrender.data
tests/test_htmlrender.py
