Metadata-Version: 1.0
Name: ZPTKit
Version: 0.4.1
Summary: Tool to use Zope Page Templates with Webware or Paste
Home-page: http://imagescape.com/software/ZPTKit/
Author: Ian Bicking
Author-email: ianb@imagescape.com
License: MIT
Platform: UNKNOWN
Classifier: Development Status :: 4 - Beta
Classifier: Environment :: Web Environment
Classifier: Intended Audience :: Developers
Classifier: License :: OSI Approved :: MIT License
Classifier: Programming Language :: Python
Classifier: Topic :: Internet :: WWW/HTTP :: Dynamic Content
Classifier: Topic :: Software Development :: Libraries :: Python Modules
Classifier: Topic :: Text Processing :: Markup :: HTML
